grokcore/error/__init__.py
grokcore/error/configure.zcml
grokcore/error/errorreport.py
grokcore/error/meta.zcml
grokcore/error/sentry.py
grokcore/error/testing.py
grokcore/error/testing.zcml
grokcore/error/zcml.py
grokcore/error/tests/__init__.py
grokcore/error/tests/test_errorreport.py
grokcore/error/tests/test_sentry.py
grokcore/error/tests/test_zcml.py
grokcore_error-5.0.dist-info/licenses/LICENSE.txt
grokcore_error-5.0.dist-info/METADATA
grokcore_error-5.0.dist-info/WHEEL
grokcore_error-5.0.dist-info/top_level.txt
grokcore_error-5.0.dist-info/RECORD
