Metadata-Version: 2.4
Name: grokcore.error
Version: 5.0
Summary: Paster support for Grok projects.
Home-page: https://github.com/zopefoundation/grokcore.error
Download-URL: http://pypi.python.org/pypi/grokcore.startup
Author: Grok Team
Author-email: zope-dev@zope.dev
License: ZPL
Keywords: zope zope3 grok grokproject WSGI Paste paster
Classifier: Environment :: Web Environment
Classifier: Intended Audience :: Developers
Classifier: License :: OSI Approved :: Zope Public License
Classifier: Programming Language :: Python
Classifier: Programming Language :: Python :: 3
Classifier: Programming Language :: Python :: 3.9
Classifier: Programming Language :: Python :: 3.10
Classifier: Programming Language :: Python :: 3.11
Classifier: Programming Language :: Python :: 3.12
Classifier: Programming Language :: Python :: 3.13
Classifier: Programming Language :: Python :: Implementation
Classifier: Programming Language :: Python :: Implementation :: CPython
Classifier: Programming Language :: Python :: Implementation :: PyPy
Classifier: Framework :: Zope :: 3
Requires-Python: >=3.9
License-File: LICENSE.txt
Requires-Dist: grokcore.component
Requires-Dist: setuptools
Requires-Dist: zope.component
Requires-Dist: zope.configuration
Requires-Dist: zope.error
Requires-Dist: zope.interface
Requires-Dist: zope.publisher
Provides-Extra: test
Requires-Dist: zope.testing; extra == "test"
Requires-Dist: zope.testrunner>=6.4; extra == "test"
Dynamic: author
Dynamic: author-email
Dynamic: classifier
Dynamic: description
Dynamic: download-url
Dynamic: home-page
Dynamic: keywords
Dynamic: license
Dynamic: license-file
Dynamic: provides-extra
Dynamic: requires-dist
Dynamic: requires-python
Dynamic: summary
